X_AI/__init__.py
X_AI/ImageClassification/Classify.py
X_AI/ImageClassification/__init__.py
X_AI-0.0.4.dist-info/LICENSE.txt
X_AI-0.0.4.dist-info/METADATA
X_AI-0.0.4.dist-info/WHEEL
X_AI-0.0.4.dist-info/top_level.txt
X_AI-0.0.4.dist-info/RECORD
