Metadata-Version: 2.1
Name: X-AI
Version: 0.0.4
Summary: A Package for AI projects
Home-page: https://github.com/sujith2303/X_AI
Author: SUJITH ANUMALA
Author-email: sujithanumala23@gmail.com
License: UNKNOWN
Project-URL: Bug Tracker, https://github.com/sujith2303/X_AI/issues
Platform: UNKNOWN
Classifier: Programming Language :: Python :: 3
Classifier: License :: OSI Approved :: MIT License
Classifier: Operating System :: OS Independent
Requires-Python: >=3.6
License-File: LICENSE.txt
